{"nodes": [{"id": "c_users_qemu_documents_sigefa_legacy_sigefa_entidades_clsingresoegreso_cs", "label": "clsIngresoEgreso.cs", "file_type": "code", "source_file": "SIGEFA.Entidades/clsIngresoEgreso.cs", "source_location": "L1"}, {"id": "sigefa_entidades_clsingresoegreso_clsingresoegreso", "label": "clsIngresoEgreso", "file_type": "code", "source_file": "SIGEFA.Entidades/clsIngresoEgreso.cs", "source_location": "L3"}, {"id": "int", "label": "int", "file_type": "code", "source_file": "SIGEFA.Entidades/clsIngresoEgreso.cs", "source_location": "L5"}, {"id": "string", "label": "string", "file_type": "code", "source_file": "SIGEFA.Entidades/clsIngresoEgreso.cs", "source_location": "L7"}], "edges": [{"source": "c_users_qemu_documents_sigefa_legacy_sigefa_entidades_clsingresoegreso_cs", "target": "sigefa_entidades_clsingresoegreso_clsingresoegreso", "relation": "contains", "confidence": "EXTRACTED", "source_file": "SIGEFA.Entidades/clsIngresoEgreso.cs", "source_location": "L3", "weight": 1.0}, {"source": "sigefa_entidades_clsingresoegreso_clsingresoegreso", "target": "int", "relation": "references", "confidence": "EXTRACTED", "source_file": "SIGEFA.Entidades/clsIngresoEgreso.cs", "source_location": "L5", "weight": 1.0, "context": "field"}, {"source": "sigefa_entidades_clsingresoegreso_clsingresoegreso", "target": "string", "relation": "references", "confidence": "EXTRACTED", "source_file": "SIGEFA.Entidades/clsIngresoEgreso.cs", "source_location": "L7", "weight": 1.0, "context": "field"}, {"source": "sigefa_entidades_clsingresoegreso_clsingresoegreso", "target": "int", "relation": "references", "confidence": "EXTRACTED", "source_file": "SIGEFA.Entidades/clsIngresoEgreso.cs", "source_location": "L9", "weight": 1.0, "context": "field"}, {"source": "sigefa_entidades_clsingresoegreso_clsingresoegreso", "target": "int", "relation": "references", "confidence": "EXTRACTED", "source_file": "SIGEFA.Entidades/clsIngresoEgreso.cs", "source_location": "L11", "weight": 1.0, "context": "field"}], "raw_calls": []}