{"nodes": [{"id": "c_users_qemu_documents_sigefa_legacy_sigefa_administradores_clsadmusuario_cs", "label": "clsAdmUsuario.cs", "file_type": "code", "source_file": "SIGEFA.Administradores/clsAdmUsuario.cs", "source_location": "L1"}, {"id": "sigefa_administradores_clsadmusuario_clsadmusuario", "label": "clsAdmUsuario", "file_type": "code", "source_file": "SIGEFA.Administradores/clsAdmUsuario.cs", "source_location": "L11"}, {"id": "iusuario", "label": "IUsuario", "file_type": "code", "source_file": "SIGEFA.Administradores/clsAdmUsuario.cs", "source_location": "L13"}, {"id": "sigefa_administradores_clsadmusuario_clsadmusuario_insert", "label": ".insert()", "file_type": "code", "source_file": "SIGEFA.Administradores/clsAdmUsuario.cs", "source_location": "L15"}, {"id": "clsusuario", "label": "clsUsuario", "file_type": "code", "source_file": "SIGEFA.Administradores/clsAdmUsuario.cs", "source_location": "L15"}, {"id": "sigefa_administradores_clsadmusuario_clsadmusuario_update", "label": ".update()", "file_type": "code", "source_file": "SIGEFA.Administradores/clsAdmUsuario.cs", "source_location": "L32"}, {"id": "sigefa_administradores_clsadmusuario_clsadmusuario_verificausuario", "label": ".verificaUsuario()", "file_type": "code", "source_file": "SIGEFA.Administradores/clsAdmUsuario.cs", "source_location": "L45"}, {"id": "sigefa_administradores_clsadmusuario_clsadmusuario_delete", "label": ".delete()", "file_type": "code", "source_file": "SIGEFA.Administradores/clsAdmUsuario.cs", "source_location": "L58"}, {"id": "sigefa_administradores_clsadmusuario_clsadmusuario_muestrausuarios", "label": ".MuestraUsuarios()", "file_type": "code", "source_file": "SIGEFA.Administradores/clsAdmUsuario.cs", "source_location": "L71"}, {"id": "datatable", "label": "DataTable", "file_type": "code", "source_file": "SIGEFA.Administradores/clsAdmUsuario.cs", "source_location": "L71"}, {"id": "sigefa_administradores_clsadmusuario_clsadmusuario_muestrausuariosxnivel", "label": ".MuestraUsuariosxNivel()", "file_type": "code", "source_file": "SIGEFA.Administradores/clsAdmUsuario.cs", "source_location": "L84"}, {"id": "sigefa_administradores_clsadmusuario_clsadmusuario_listausuarios_empresa", "label": ".ListaUsuarios_Empresa()", "file_type": "code", "source_file": "SIGEFA.Administradores/clsAdmUsuario.cs", "source_location": "L97"}, {"id": "sigefa_administradores_clsadmusuario_clsadmusuario_muestrausuario", "label": ".MuestraUsuario()", "file_type": "code", "source_file": "SIGEFA.Administradores/clsAdmUsuario.cs", "source_location": "L110"}, {"id": "sigefa_administradores_clsadmusuario_clsadmusuario_muestrausuariosinadmin", "label": ".MuestraUsuarioSinAdmin()", "file_type": "code", "source_file": "SIGEFA.Administradores/clsAdmUsuario.cs", "source_location": "L136"}, {"id": "sigefa_administradores_clsadmusuario_clsadmusuario_muestrausuarionivel", "label": ".MuestraUsuarioNivel()", "file_type": "code", "source_file": "SIGEFA.Administradores/clsAdmUsuario.cs", "source_location": "L149"}, {"id": "sigefa_administradores_clsadmusuario_clsadmusuario_establecelogin", "label": ".EstableceLogin()", "file_type": "code", "source_file": "SIGEFA.Administradores/clsAdmUsuario.cs", "source_location": "L162"}, {"id": "sigefa_administradores_clsadmusuario_clsadmusuario_listacorreousuarios", "label": ".ListaCorreoUsuarios()", "file_type": "code", "source_file": "SIGEFA.Administradores/clsAdmUsuario.cs", "source_location": "L175"}, {"id": "sigefa_administradores_clsadmusuario_clsadmusuario_correotesoreria", "label": ".correoTesoreria()", "file_type": "code", "source_file": "SIGEFA.Administradores/clsAdmUsuario.cs", "source_location": "L188"}, {"id": "sigefa_administradores_clsadmusuario_clsadmusuario_listaniveles", "label": ".ListaNiveles()", "file_type": "code", "source_file": "SIGEFA.Administradores/clsAdmUsuario.cs", "source_location": "L201"}, {"id": "sigefa_administradores_clsadmusuario_clsadmusuario_cargausuarios", "label": ".CargaUsuarios()", "file_type": "code", "source_file": "SIGEFA.Administradores/clsAdmUsuario.cs", "source_location": "L214"}, {"id": "sigefa_administradores_clsadmusuario_clsadmusuario_cargaautorizador", "label": ".cargaAutorizador()", "file_type": "code", "source_file": "SIGEFA.Administradores/clsAdmUsuario.cs", "source_location": "L227"}, {"id": "sigefa_administradores_clsadmusuario_clsadmusuario_listausuariosdespacho", "label": ".ListaUsuariosDespacho()", "file_type": "code", "source_file": "SIGEFA.Administradores/clsAdmUsuario.cs", "source_location": "L240"}], "edges": [{"source": "c_users_qemu_documents_sigefa_legacy_sigefa_administradores_clsadmusuario_cs", "target": "system", "relation": "imports", "context": "import", "confidence": "EXTRACTED", "source_file": "SIGEFA.Administradores/clsAdmUsuario.cs", "source_location": "L1", "weight": 1.0}, {"source": "c_users_qemu_documents_sigefa_legacy_sigefa_administradores_clsadmusuario_cs", "target": "data", "relation": "imports", "context": "import", "confidence": "EXTRACTED", "source_file": "SIGEFA.Administradores/clsAdmUsuario.cs", "source_location": "L2", "weight": 1.0}, {"source": "c_users_qemu_documents_sigefa_legacy_sigefa_administradores_clsadmusuario_cs", "target": "forms", "relation": "imports", "context": "import", "confidence": "EXTRACTED", "source_file": "SIGEFA.Administradores/clsAdmUsuario.cs", "source_location": "L3", "weight": 1.0}, {"source": "c_users_qemu_documents_sigefa_legacy_sigefa_administradores_clsadmusuario_cs", "target": "dotnetbar", "relation": "imports", "context": "import", "confidence": "EXTRACTED", "source_file": "SIGEFA.Administradores/clsAdmUsuario.cs", "source_location": "L4", "weight": 1.0}, {"source": "c_users_qemu_documents_sigefa_legacy_sigefa_administradores_clsadmusuario_cs", "target": "entidades", "relation": "imports", "context": "import", "confidence": "EXTRACTED", "source_file": "SIGEFA.Administradores/clsAdmUsuario.cs", "source_location": "L5", "weight": 1.0}, {"source": "c_users_qemu_documents_sigefa_legacy_sigefa_administradores_clsadmusuario_cs", "target": "interfaces", "relation": "imports", "context": "import", "confidence": "EXTRACTED", "source_file": "SIGEFA.Administradores/clsAdmUsuario.cs", "source_location": "L6", "weight": 1.0}, {"source": "c_users_qemu_documents_sigefa_legacy_sigefa_administradores_clsadmusuario_cs", "target": "intermysql", "relation": "imports", "context": "import", "confidence": "EXTRACTED", "source_file": "SIGEFA.Administradores/clsAdmUsuario.cs", "source_location": "L7", "weight": 1.0}, {"source": "c_users_qemu_documents_sigefa_legacy_sigefa_administradores_clsadmusuario_cs", "target": "sigefa_administradores_clsadmusuario_clsadmusuario", "relation": "contains", "confidence": "EXTRACTED", "source_file": "SIGEFA.Administradores/clsAdmUsuario.cs", "source_location": "L11", "weight": 1.0}, {"source": "sigefa_administradores_clsadmusuario_clsadmusuario", "target": "iusuario", "relation": "references", "confidence": "EXTRACTED", "source_file": "SIGEFA.Administradores/clsAdmUsuario.cs", "source_location": "L13", "weight": 1.0, "context": "field"}, {"source": "sigefa_administradores_clsadmusuario_clsadmusuario", "target": "sigefa_administradores_clsadmusuario_clsadmusuario_insert", "relation": "method", "confidence": "EXTRACTED", "source_file": "SIGEFA.Administradores/clsAdmUsuario.cs", "source_location": "L15", "weight": 1.0}, {"source": "sigefa_administradores_clsadmusuario_clsadmusuario_insert", "target": "clsusuario", "relation": "references", "confidence": "EXTRACTED", "source_file": "SIGEFA.Administradores/clsAdmUsuario.cs", "source_location": "L15", "weight": 1.0, "context": "parameter_type"}, {"source": "sigefa_administradores_clsadmusuario_clsadmusuario", "target": "sigefa_administradores_clsadmusuario_clsadmusuario_update", "relation": "method", "confidence": "EXTRACTED", "source_file": "SIGEFA.Administradores/clsAdmUsuario.cs", "source_location": "L32", "weight": 1.0}, {"source": "sigefa_administradores_clsadmusuario_clsadmusuario_update", "target": "clsusuario", "relation": "references", "confidence": "EXTRACTED", "source_file": "SIGEFA.Administradores/clsAdmUsuario.cs", "source_location": "L32", "weight": 1.0, "context": "parameter_type"}, {"source": "sigefa_administradores_clsadmusuario_clsadmusuario", "target": "sigefa_administradores_clsadmusuario_clsadmusuario_verificausuario", "relation": "method", "confidence": "EXTRACTED", "source_file": "SIGEFA.Administradores/clsAdmUsuario.cs", "source_location": "L45", "weight": 1.0}, {"source": "sigefa_administradores_clsadmusuario_clsadmusuario", "target": "sigefa_administradores_clsadmusuario_clsadmusuario_delete", "relation": "method", "confidence": "EXTRACTED", "source_file": "SIGEFA.Administradores/clsAdmUsuario.cs", "source_location": "L58", "weight": 1.0}, {"source": "sigefa_administradores_clsadmusuario_clsadmusuario", "target": "sigefa_administradores_clsadmusuario_clsadmusuario_muestrausuarios", "relation": "method", "confidence": "EXTRACTED", "source_file": "SIGEFA.Administradores/clsAdmUsuario.cs", "source_location": "L71", "weight": 1.0}, {"source": "sigefa_administradores_clsadmusuario_clsadmusuario_muestrausuarios", "target": "datatable", "relation": "references", "confidence": "EXTRACTED", "source_file": "SIGEFA.Administradores/clsAdmUsuario.cs", "source_location": "L71", "weight": 1.0, "context": "return_type"}, {"source": "sigefa_administradores_clsadmusuario_clsadmusuario", "target": "sigefa_administradores_clsadmusuario_clsadmusuario_muestrausuariosxnivel", "relation": "method", "confidence": "EXTRACTED", "source_file": "SIGEFA.Administradores/clsAdmUsuario.cs", "source_location": "L84", "weight": 1.0}, {"source": "sigefa_administradores_clsadmusuario_clsadmusuario_muestrausuariosxnivel", "target": "datatable", "relation": "references", "confidence": "EXTRACTED", "source_file": "SIGEFA.Administradores/clsAdmUsuario.cs", "source_location": "L84", "weight": 1.0, "context": "return_type"}, {"source": "sigefa_administradores_clsadmusuario_clsadmusuario", "target": "sigefa_administradores_clsadmusuario_clsadmusuario_listausuarios_empresa", "relation": "method", "confidence": "EXTRACTED", "source_file": "SIGEFA.Administradores/clsAdmUsuario.cs", "source_location": "L97", "weight": 1.0}, {"source": "sigefa_administradores_clsadmusuario_clsadmusuario_listausuarios_empresa", "target": "datatable", "relation": "references", "confidence": "EXTRACTED", "source_file": "SIGEFA.Administradores/clsAdmUsuario.cs", "source_location": "L97", "weight": 1.0, "context": "return_type"}, {"source": "sigefa_administradores_clsadmusuario_clsadmusuario", "target": "sigefa_administradores_clsadmusuario_clsadmusuario_muestrausuario", "relation": "method", "confidence": "EXTRACTED", "source_file": "SIGEFA.Administradores/clsAdmUsuario.cs", "source_location": "L110", "weight": 1.0}, {"source": "sigefa_administradores_clsadmusuario_clsadmusuario_muestrausuario", "target": "clsusuario", "relation": "references", "confidence": "EXTRACTED", "source_file": "SIGEFA.Administradores/clsAdmUsuario.cs", "source_location": "L110", "weight": 1.0, "context": "return_type"}, {"source": "sigefa_administradores_clsadmusuario_clsadmusuario", "target": "sigefa_administradores_clsadmusuario_clsadmusuario_muestrausuario", "relation": "method", "confidence": "EXTRACTED", "source_file": "SIGEFA.Administradores/clsAdmUsuario.cs", "source_location": "L123", "weight": 1.0}, {"source": "sigefa_administradores_clsadmusuario_clsadmusuario_muestrausuario", "target": "clsusuario", "relation": "references", "confidence": "EXTRACTED", "source_file": "SIGEFA.Administradores/clsAdmUsuario.cs", "source_location": "L123", "weight": 1.0, "context": "return_type"}, {"source": "sigefa_administradores_clsadmusuario_clsadmusuario", "target": "sigefa_administradores_clsadmusuario_clsadmusuario_muestrausuariosinadmin", "relation": "method", "confidence": "EXTRACTED", "source_file": "SIGEFA.Administradores/clsAdmUsuario.cs", "source_location": "L136", "weight": 1.0}, {"source": "sigefa_administradores_clsadmusuario_clsadmusuario_muestrausuariosinadmin", "target": "clsusuario", "relation": "references", "confidence": "EXTRACTED", "source_file": "SIGEFA.Administradores/clsAdmUsuario.cs", "source_location": "L136", "weight": 1.0, "context": "return_type"}, {"source": "sigefa_administradores_clsadmusuario_clsadmusuario", "target": "sigefa_administradores_clsadmusuario_clsadmusuario_muestrausuarionivel", "relation": "method", "confidence": "EXTRACTED", "source_file": "SIGEFA.Administradores/clsAdmUsuario.cs", "source_location": "L149", "weight": 1.0}, {"source": "sigefa_administradores_clsadmusuario_clsadmusuario_muestrausuarionivel", "target": "clsusuario", "relation": "references", "confidence": "EXTRACTED", "source_file": "SIGEFA.Administradores/clsAdmUsuario.cs", "source_location": "L149", "weight": 1.0, "context": "return_type"}, {"source": "sigefa_administradores_clsadmusuario_clsadmusuario", "target": "sigefa_administradores_clsadmusuario_clsadmusuario_establecelogin", "relation": "method", "confidence": "EXTRACTED", "source_file": "SIGEFA.Administradores/clsAdmUsuario.cs", "source_location": "L162", "weight": 1.0}, {"source": "sigefa_administradores_clsadmusuario_clsadmusuario_establecelogin", "target": "clsusuario", "relation": "references", "confidence": "EXTRACTED", "source_file": "SIGEFA.Administradores/clsAdmUsuario.cs", "source_location": "L162", "weight": 1.0, "context": "parameter_type"}, {"source": "sigefa_administradores_clsadmusuario_clsadmusuario", "target": "sigefa_administradores_clsadmusuario_clsadmusuario_listacorreousuarios", "relation": "method", "confidence": "EXTRACTED", "source_file": "SIGEFA.Administradores/clsAdmUsuario.cs", "source_location": "L175", "weight": 1.0}, {"source": "sigefa_administradores_clsadmusuario_clsadmusuario_listacorreousuarios", "target": "datatable", "relation": "references", "confidence": "EXTRACTED", "source_file": "SIGEFA.Administradores/clsAdmUsuario.cs", "source_location": "L175", "weight": 1.0, "context": "return_type"}, {"source": "sigefa_administradores_clsadmusuario_clsadmusuario", "target": "sigefa_administradores_clsadmusuario_clsadmusuario_correotesoreria", "relation": "method", "confidence": "EXTRACTED", "source_file": "SIGEFA.Administradores/clsAdmUsuario.cs", "source_location": "L188", "weight": 1.0}, {"source": "sigefa_administradores_clsadmusuario_clsadmusuario_correotesoreria", "target": "datatable", "relation": "references", "confidence": "EXTRACTED", "source_file": "SIGEFA.Administradores/clsAdmUsuario.cs", "source_location": "L188", "weight": 1.0, "context": "return_type"}, {"source": "sigefa_administradores_clsadmusuario_clsadmusuario", "target": "sigefa_administradores_clsadmusuario_clsadmusuario_listaniveles", "relation": "method", "confidence": "EXTRACTED", "source_file": "SIGEFA.Administradores/clsAdmUsuario.cs", "source_location": "L201", "weight": 1.0}, {"source": "sigefa_administradores_clsadmusuario_clsadmusuario_listaniveles", "target": "datatable", "relation": "references", "confidence": "EXTRACTED", "source_file": "SIGEFA.Administradores/clsAdmUsuario.cs", "source_location": "L201", "weight": 1.0, "context": "return_type"}, {"source": "sigefa_administradores_clsadmusuario_clsadmusuario", "target": "sigefa_administradores_clsadmusuario_clsadmusuario_cargausuarios", "relation": "method", "confidence": "EXTRACTED", "source_file": "SIGEFA.Administradores/clsAdmUsuario.cs", "source_location": "L214", "weight": 1.0}, {"source": "sigefa_administradores_clsadmusuario_clsadmusuario_cargausuarios", "target": "datatable", "relation": "references", "confidence": "EXTRACTED", "source_file": "SIGEFA.Administradores/clsAdmUsuario.cs", "source_location": "L214", "weight": 1.0, "context": "return_type"}, {"source": "sigefa_administradores_clsadmusuario_clsadmusuario", "target": "sigefa_administradores_clsadmusuario_clsadmusuario_cargaautorizador", "relation": "method", "confidence": "EXTRACTED", "source_file": "SIGEFA.Administradores/clsAdmUsuario.cs", "source_location": "L227", "weight": 1.0}, {"source": "sigefa_administradores_clsadmusuario_clsadmusuario_cargaautorizador", "target": "clsusuario", "relation": "references", "confidence": "EXTRACTED", "source_file": "SIGEFA.Administradores/clsAdmUsuario.cs", "source_location": "L227", "weight": 1.0, "context": "return_type"}, {"source": "sigefa_administradores_clsadmusuario_clsadmusuario", "target": "sigefa_administradores_clsadmusuario_clsadmusuario_listausuariosdespacho", "relation": "method", "confidence": "EXTRACTED", "source_file": "SIGEFA.Administradores/clsAdmUsuario.cs", "source_location": "L240", "weight": 1.0}, {"source": "sigefa_administradores_clsadmusuario_clsadmusuario_listausuariosdespacho", "target": "datatable", "relation": "references", "confidence": "EXTRACTED", "source_file": "SIGEFA.Administradores/clsAdmUsuario.cs", "source_location": "L240", "weight": 1.0, "context": "return_type"}], "raw_calls": [{"caller_nid": "sigefa_administradores_clsadmusuario_clsadmusuario_insert", "callee": "Insert", "is_member_call": true, "source_file": "C:\\Users\\qemu\\Documents\\sigefa_legacy\\SIGEFA.Administradores\\clsAdmUsuario.cs", "source_location": "L19"}, {"caller_nid": "sigefa_administradores_clsadmusuario_clsadmusuario_insert", "callee": "Contains", "is_member_call": true, "source_file": "C:\\Users\\qemu\\Documents\\sigefa_legacy\\SIGEFA.Administradores\\clsAdmUsuario.cs", "source_location": "L23"}, {"caller_nid": "sigefa_administradores_clsadmusuario_clsadmusuario_insert", "callee": "Show", "is_member_call": true, "source_file": "C:\\Users\\qemu\\Documents\\sigefa_legacy\\SIGEFA.Administradores\\clsAdmUsuario.cs", "source_location": "L25"}, {"caller_nid": "sigefa_administradores_clsadmusuario_clsadmusuario_insert", "callee": "Show", "is_member_call": true, "source_file": "C:\\Users\\qemu\\Documents\\sigefa_legacy\\SIGEFA.Administradores\\clsAdmUsuario.cs", "source_location": "L27"}, {"caller_nid": "sigefa_administradores_clsadmusuario_clsadmusuario_update", "callee": "Update", "is_member_call": true, "source_file": "C:\\Users\\qemu\\Documents\\sigefa_legacy\\SIGEFA.Administradores\\clsAdmUsuario.cs", "source_location": "L36"}, {"caller_nid": "sigefa_administradores_clsadmusuario_clsadmusuario_update", "callee": "Show", "is_member_call": true, "source_file": "C:\\Users\\qemu\\Documents\\sigefa_legacy\\SIGEFA.Administradores\\clsAdmUsuario.cs", "source_location": "L40"}, {"caller_nid": "sigefa_administradores_clsadmusuario_clsadmusuario_verificausuario", "callee": "Show", "is_member_call": true, "source_file": "C:\\Users\\qemu\\Documents\\sigefa_legacy\\SIGEFA.Administradores\\clsAdmUsuario.cs", "source_location": "L53"}, {"caller_nid": "sigefa_administradores_clsadmusuario_clsadmusuario_delete", "callee": "Delete", "is_member_call": true, "source_file": "C:\\Users\\qemu\\Documents\\sigefa_legacy\\SIGEFA.Administradores\\clsAdmUsuario.cs", "source_location": "L62"}, {"caller_nid": "sigefa_administradores_clsadmusuario_clsadmusuario_delete", "callee": "Show", "is_member_call": true, "source_file": "C:\\Users\\qemu\\Documents\\sigefa_legacy\\SIGEFA.Administradores\\clsAdmUsuario.cs", "source_location": "L66"}, {"caller_nid": "sigefa_administradores_clsadmusuario_clsadmusuario_muestrausuarios", "callee": "ListaUsuarios", "is_member_call": true, "source_file": "C:\\Users\\qemu\\Documents\\sigefa_legacy\\SIGEFA.Administradores\\clsAdmUsuario.cs", "source_location": "L75"}, {"caller_nid": "sigefa_administradores_clsadmusuario_clsadmusuario_muestrausuarios", "callee": "Show", "is_member_call": true, "source_file": "C:\\Users\\qemu\\Documents\\sigefa_legacy\\SIGEFA.Administradores\\clsAdmUsuario.cs", "source_location": "L79"}, {"caller_nid": "sigefa_administradores_clsadmusuario_clsadmusuario_muestrausuariosxnivel", "callee": "ListaUsuariosxNivel", "is_member_call": true, "source_file": "C:\\Users\\qemu\\Documents\\sigefa_legacy\\SIGEFA.Administradores\\clsAdmUsuario.cs", "source_location": "L88"}, {"caller_nid": "sigefa_administradores_clsadmusuario_clsadmusuario_muestrausuariosxnivel", "callee": "Show", "is_member_call": true, "source_file": "C:\\Users\\qemu\\Documents\\sigefa_legacy\\SIGEFA.Administradores\\clsAdmUsuario.cs", "source_location": "L92"}, {"caller_nid": "sigefa_administradores_clsadmusuario_clsadmusuario_listausuarios_empresa", "callee": "Show", "is_member_call": true, "source_file": "C:\\Users\\qemu\\Documents\\sigefa_legacy\\SIGEFA.Administradores\\clsAdmUsuario.cs", "source_location": "L105"}, {"caller_nid": "sigefa_administradores_clsadmusuario_clsadmusuario_muestrausuario", "callee": "CargaUsuario", "is_member_call": true, "source_file": "C:\\Users\\qemu\\Documents\\sigefa_legacy\\SIGEFA.Administradores\\clsAdmUsuario.cs", "source_location": "L114"}, {"caller_nid": "sigefa_administradores_clsadmusuario_clsadmusuario_muestrausuario", "callee": "Show", "is_member_call": true, "source_file": "C:\\Users\\qemu\\Documents\\sigefa_legacy\\SIGEFA.Administradores\\clsAdmUsuario.cs", "source_location": "L118"}, {"caller_nid": "sigefa_administradores_clsadmusuario_clsadmusuario_muestrausuario", "callee": "cargaUsuario", "is_member_call": true, "source_file": "C:\\Users\\qemu\\Documents\\sigefa_legacy\\SIGEFA.Administradores\\clsAdmUsuario.cs", "source_location": "L127"}, {"caller_nid": "sigefa_administradores_clsadmusuario_clsadmusuario_muestrausuario", "callee": "Show", "is_member_call": true, "source_file": "C:\\Users\\qemu\\Documents\\sigefa_legacy\\SIGEFA.Administradores\\clsAdmUsuario.cs", "source_location": "L131"}, {"caller_nid": "sigefa_administradores_clsadmusuario_clsadmusuario_muestrausuariosinadmin", "callee": "CargaUsuarioSinAdmin", "is_member_call": true, "source_file": "C:\\Users\\qemu\\Documents\\sigefa_legacy\\SIGEFA.Administradores\\clsAdmUsuario.cs", "source_location": "L140"}, {"caller_nid": "sigefa_administradores_clsadmusuario_clsadmusuario_muestrausuariosinadmin", "callee": "Show", "is_member_call": true, "source_file": "C:\\Users\\qemu\\Documents\\sigefa_legacy\\SIGEFA.Administradores\\clsAdmUsuario.cs", "source_location": "L144"}, {"caller_nid": "sigefa_administradores_clsadmusuario_clsadmusuario_muestrausuarionivel", "callee": "CargaUsuarioNivel", "is_member_call": true, "source_file": "C:\\Users\\qemu\\Documents\\sigefa_legacy\\SIGEFA.Administradores\\clsAdmUsuario.cs", "source_location": "L153"}, {"caller_nid": "sigefa_administradores_clsadmusuario_clsadmusuario_muestrausuarionivel", "callee": "Show", "is_member_call": true, "source_file": "C:\\Users\\qemu\\Documents\\sigefa_legacy\\SIGEFA.Administradores\\clsAdmUsuario.cs", "source_location": "L157"}, {"caller_nid": "sigefa_administradores_clsadmusuario_clsadmusuario_establecelogin", "callee": "Login", "is_member_call": true, "source_file": "C:\\Users\\qemu\\Documents\\sigefa_legacy\\SIGEFA.Administradores\\clsAdmUsuario.cs", "source_location": "L166"}, {"caller_nid": "sigefa_administradores_clsadmusuario_clsadmusuario_establecelogin", "callee": "Show", "is_member_call": true, "source_file": "C:\\Users\\qemu\\Documents\\sigefa_legacy\\SIGEFA.Administradores\\clsAdmUsuario.cs", "source_location": "L170"}, {"caller_nid": "sigefa_administradores_clsadmusuario_clsadmusuario_listacorreousuarios", "callee": "ListaCorreosUsuarios", "is_member_call": true, "source_file": "C:\\Users\\qemu\\Documents\\sigefa_legacy\\SIGEFA.Administradores\\clsAdmUsuario.cs", "source_location": "L179"}, {"caller_nid": "sigefa_administradores_clsadmusuario_clsadmusuario_listacorreousuarios", "callee": "Show", "is_member_call": true, "source_file": "C:\\Users\\qemu\\Documents\\sigefa_legacy\\SIGEFA.Administradores\\clsAdmUsuario.cs", "source_location": "L183"}, {"caller_nid": "sigefa_administradores_clsadmusuario_clsadmusuario_correotesoreria", "callee": "Show", "is_member_call": true, "source_file": "C:\\Users\\qemu\\Documents\\sigefa_legacy\\SIGEFA.Administradores\\clsAdmUsuario.cs", "source_location": "L196"}, {"caller_nid": "sigefa_administradores_clsadmusuario_clsadmusuario_listaniveles", "callee": "Show", "is_member_call": true, "source_file": "C:\\Users\\qemu\\Documents\\sigefa_legacy\\SIGEFA.Administradores\\clsAdmUsuario.cs", "source_location": "L209"}, {"caller_nid": "sigefa_administradores_clsadmusuario_clsadmusuario_cargausuarios", "callee": "Show", "is_member_call": true, "source_file": "C:\\Users\\qemu\\Documents\\sigefa_legacy\\SIGEFA.Administradores\\clsAdmUsuario.cs", "source_location": "L222"}, {"caller_nid": "sigefa_administradores_clsadmusuario_clsadmusuario_cargaautorizador", "callee": "Show", "is_member_call": true, "source_file": "C:\\Users\\qemu\\Documents\\sigefa_legacy\\SIGEFA.Administradores\\clsAdmUsuario.cs", "source_location": "L235"}, {"caller_nid": "sigefa_administradores_clsadmusuario_clsadmusuario_listausuariosdespacho", "callee": "Show", "is_member_call": true, "source_file": "C:\\Users\\qemu\\Documents\\sigefa_legacy\\SIGEFA.Administradores\\clsAdmUsuario.cs", "source_location": "L248"}]}