{"nodes": [{"id": "c_users_qemu_documents_sigefa_legacy_sigefa_entidades_clsdetallenotacredito_cs", "label": "clsDetalleNotaCredito.cs", "file_type": "code", "source_file": "SIGEFA.Entidades/clsDetalleNotaCredito.cs", "source_location": "L1"}, {"id": "sigefa_entidades_clsdetallenotacredito_clsdetallenotacredito", "label": "clsDetalleNotaCredito", "file_type": "code", "source_file": "SIGEFA.Entidades/clsDetalleNotaCredito.cs", "source_location": "L5"}, {"id": "int", "label": "int", "file_type": "code", "source_file": "SIGEFA.Entidades/clsDetalleNotaCredito.cs", "source_location": "L7"}, {"id": "string", "label": "string", "file_type": "code", "source_file": "SIGEFA.Entidades/clsDetalleNotaCredito.cs", "source_location": "L13"}, {"id": "double", "label": "double", "file_type": "code", "source_file": "SIGEFA.Entidades/clsDetalleNotaCredito.cs", "source_location": "L23"}, {"id": "bool", "label": "bool", "file_type": "code", "source_file": "SIGEFA.Entidades/clsDetalleNotaCredito.cs", "source_location": "L49"}, {"id": "datetime", "label": "DateTime", "file_type": "code", "source_file": "SIGEFA.Entidades/clsDetalleNotaCredito.cs", "source_location": "L51"}], "edges": [{"source": "c_users_qemu_documents_sigefa_legacy_sigefa_entidades_clsdetallenotacredito_cs", "target": "system", "relation": "imports", "context": "import", "confidence": "EXTRACTED", "source_file": "SIGEFA.Entidades/clsDetalleNotaCredito.cs", "source_location": "L1", "weight": 1.0}, {"source": "c_users_qemu_documents_sigefa_legacy_sigefa_entidades_clsdetallenotacredito_cs", "target": "sigefa_entidades_clsdetallenotacredito_clsdetallenotacredito", "relation": "contains", "confidence": "EXTRACTED", "source_file": "SIGEFA.Entidades/clsDetalleNotaCredito.cs", "source_location": "L5", "weight": 1.0}, {"source": "sigefa_entidades_clsdetallenotacredito_clsdetallenotacredito", "target": "int", "relation": "references", "confidence": "EXTRACTED", "source_file": "SIGEFA.Entidades/clsDetalleNotaCredito.cs", "source_location": "L7", "weight": 1.0, "context": "field"}, {"source": "sigefa_entidades_clsdetallenotacredito_clsdetallenotacredito", "target": "int", "relation": "references", "confidence": "EXTRACTED", "source_file": "SIGEFA.Entidades/clsDetalleNotaCredito.cs", "source_location": "L9", "weight": 1.0, "context": "field"}, {"source": "sigefa_entidades_clsdetallenotacredito_clsdetallenotacredito", "target": "int", "relation": "references", "confidence": "EXTRACTED", "source_file": "SIGEFA.Entidades/clsDetalleNotaCredito.cs", "source_location": "L11", "weight": 1.0, "context": "field"}, {"source": "sigefa_entidades_clsdetallenotacredito_clsdetallenotacredito", "target": "string", "relation": "references", "confidence": "EXTRACTED", "source_file": "SIGEFA.Entidades/clsDetalleNotaCredito.cs", "source_location": "L13", "weight": 1.0, "context": "field"}, {"source": "sigefa_entidades_clsdetallenotacredito_clsdetallenotacredito", "target": "int", "relation": "references", "confidence": "EXTRACTED", "source_file": "SIGEFA.Entidades/clsDetalleNotaCredito.cs", "source_location": "L15", "weight": 1.0, "context": "field"}, {"source": "sigefa_entidades_clsdetallenotacredito_clsdetallenotacredito", "target": "int", "relation": "references", "confidence": "EXTRACTED", "source_file": "SIGEFA.Entidades/clsDetalleNotaCredito.cs", "source_location": "L17", "weight": 1.0, "context": "field"}, {"source": "sigefa_entidades_clsdetallenotacredito_clsdetallenotacredito", "target": "int", "relation": "references", "confidence": "EXTRACTED", "source_file": "SIGEFA.Entidades/clsDetalleNotaCredito.cs", "source_location": "L19", "weight": 1.0, "context": "field"}, {"source": "sigefa_entidades_clsdetallenotacredito_clsdetallenotacredito", "target": "string", "relation": "references", "confidence": "EXTRACTED", "source_file": "SIGEFA.Entidades/clsDetalleNotaCredito.cs", "source_location": "L21", "weight": 1.0, "context": "field"}, {"source": "sigefa_entidades_clsdetallenotacredito_clsdetallenotacredito", "target": "double", "relation": "references", "confidence": "EXTRACTED", "source_file": "SIGEFA.Entidades/clsDetalleNotaCredito.cs", "source_location": "L23", "weight": 1.0, "context": "field"}, {"source": "sigefa_entidades_clsdetallenotacredito_clsdetallenotacredito", "target": "int", "relation": "references", "confidence": "EXTRACTED", "source_file": "SIGEFA.Entidades/clsDetalleNotaCredito.cs", "source_location": "L25", "weight": 1.0, "context": "field"}, {"source": "sigefa_entidades_clsdetallenotacredito_clsdetallenotacredito", "target": "double", "relation": "references", "confidence": "EXTRACTED", "source_file": "SIGEFA.Entidades/clsDetalleNotaCredito.cs", "source_location": "L27", "weight": 1.0, "context": "field"}, {"source": "sigefa_entidades_clsdetallenotacredito_clsdetallenotacredito", "target": "double", "relation": "references", "confidence": "EXTRACTED", "source_file": "SIGEFA.Entidades/clsDetalleNotaCredito.cs", "source_location": "L29", "weight": 1.0, "context": "field"}, {"source": "sigefa_entidades_clsdetallenotacredito_clsdetallenotacredito", "target": "double", "relation": "references", "confidence": "EXTRACTED", "source_file": "SIGEFA.Entidades/clsDetalleNotaCredito.cs", "source_location": "L31", "weight": 1.0, "context": "field"}, {"source": "sigefa_entidades_clsdetallenotacredito_clsdetallenotacredito", "target": "double", "relation": "references", "confidence": "EXTRACTED", "source_file": "SIGEFA.Entidades/clsDetalleNotaCredito.cs", "source_location": "L33", "weight": 1.0, "context": "field"}, {"source": "sigefa_entidades_clsdetallenotacredito_clsdetallenotacredito", "target": "double", "relation": "references", "confidence": "EXTRACTED", "source_file": "SIGEFA.Entidades/clsDetalleNotaCredito.cs", "source_location": "L35", "weight": 1.0, "context": "field"}, {"source": "sigefa_entidades_clsdetallenotacredito_clsdetallenotacredito", "target": "double", "relation": "references", "confidence": "EXTRACTED", "source_file": "SIGEFA.Entidades/clsDetalleNotaCredito.cs", "source_location": "L37", "weight": 1.0, "context": "field"}, {"source": "sigefa_entidades_clsdetallenotacredito_clsdetallenotacredito", "target": "double", "relation": "references", "confidence": "EXTRACTED", "source_file": "SIGEFA.Entidades/clsDetalleNotaCredito.cs", "source_location": "L39", "weight": 1.0, "context": "field"}, {"source": "sigefa_entidades_clsdetallenotacredito_clsdetallenotacredito", "target": "double", "relation": "references", "confidence": "EXTRACTED", "source_file": "SIGEFA.Entidades/clsDetalleNotaCredito.cs", "source_location": "L41", "weight": 1.0, "context": "field"}, {"source": "sigefa_entidades_clsdetallenotacredito_clsdetallenotacredito", "target": "double", "relation": "references", "confidence": "EXTRACTED", "source_file": "SIGEFA.Entidades/clsDetalleNotaCredito.cs", "source_location": "L43", "weight": 1.0, "context": "field"}, {"source": "sigefa_entidades_clsdetallenotacredito_clsdetallenotacredito", "target": "double", "relation": "references", "confidence": "EXTRACTED", "source_file": "SIGEFA.Entidades/clsDetalleNotaCredito.cs", "source_location": "L45", "weight": 1.0, "context": "field"}, {"source": "sigefa_entidades_clsdetallenotacredito_clsdetallenotacredito", "target": "double", "relation": "references", "confidence": "EXTRACTED", "source_file": "SIGEFA.Entidades/clsDetalleNotaCredito.cs", "source_location": "L47", "weight": 1.0, "context": "field"}, {"source": "sigefa_entidades_clsdetallenotacredito_clsdetallenotacredito", "target": "bool", "relation": "references", "confidence": "EXTRACTED", "source_file": "SIGEFA.Entidades/clsDetalleNotaCredito.cs", "source_location": "L49", "weight": 1.0, "context": "field"}, {"source": "sigefa_entidades_clsdetallenotacredito_clsdetallenotacredito", "target": "datetime", "relation": "references", "confidence": "EXTRACTED", "source_file": "SIGEFA.Entidades/clsDetalleNotaCredito.cs", "source_location": "L51", "weight": 1.0, "context": "field"}, {"source": "sigefa_entidades_clsdetallenotacredito_clsdetallenotacredito", "target": "datetime", "relation": "references", "confidence": "EXTRACTED", "source_file": "SIGEFA.Entidades/clsDetalleNotaCredito.cs", "source_location": "L53", "weight": 1.0, "context": "field"}, {"source": "sigefa_entidades_clsdetallenotacredito_clsdetallenotacredito", "target": "int", "relation": "references", "confidence": "EXTRACTED", "source_file": "SIGEFA.Entidades/clsDetalleNotaCredito.cs", "source_location": "L55", "weight": 1.0, "context": "field"}, {"source": "sigefa_entidades_clsdetallenotacredito_clsdetallenotacredito", "target": "int", "relation": "references", "confidence": "EXTRACTED", "source_file": "SIGEFA.Entidades/clsDetalleNotaCredito.cs", "source_location": "L57", "weight": 1.0, "context": "field"}], "raw_calls": []}