{"nodes": [{"id": "c_users_qemu_documents_sigefa_legacy_sigefa_entidades_clsdetalleentrega_cs", "label": "clsDetalleEntrega.cs", "file_type": "code", "source_file": "SIGEFA.Entidades/clsDetalleEntrega.cs", "source_location": "L1"}, {"id": "sigefa_entidades_clsdetalleentrega_clsdetalleentrega", "label": "clsDetalleEntrega", "file_type": "code", "source_file": "SIGEFA.Entidades/clsDetalleEntrega.cs", "source_location": "L3"}, {"id": "int", "label": "int", "file_type": "code", "source_file": "SIGEFA.Entidades/clsDetalleEntrega.cs", "source_location": "L5"}, {"id": "double", "label": "double", "file_type": "code", "source_file": "SIGEFA.Entidades/clsDetalleEntrega.cs", "source_location": "L17"}, {"id": "string", "label": "string", "file_type": "code", "source_file": "SIGEFA.Entidades/clsDetalleEntrega.cs", "source_location": "L19"}], "edges": [{"source": "c_users_qemu_documents_sigefa_legacy_sigefa_entidades_clsdetalleentrega_cs", "target": "sigefa_entidades_clsdetalleentrega_clsdetalleentrega", "relation": "contains", "confidence": "EXTRACTED", "source_file": "SIGEFA.Entidades/clsDetalleEntrega.cs", "source_location": "L3", "weight": 1.0}, {"source": "sigefa_entidades_clsdetalleentrega_clsdetalleentrega", "target": "int", "relation": "references", "confidence": "EXTRACTED", "source_file": "SIGEFA.Entidades/clsDetalleEntrega.cs", "source_location": "L5", "weight": 1.0, "context": "field"}, {"source": "sigefa_entidades_clsdetalleentrega_clsdetalleentrega", "target": "int", "relation": "references", "confidence": "EXTRACTED", "source_file": "SIGEFA.Entidades/clsDetalleEntrega.cs", "source_location": "L7", "weight": 1.0, "context": "field"}, {"source": "sigefa_entidades_clsdetalleentrega_clsdetalleentrega", "target": "int", "relation": "references", "confidence": "EXTRACTED", "source_file": "SIGEFA.Entidades/clsDetalleEntrega.cs", "source_location": "L9", "weight": 1.0, "context": "field"}, {"source": "sigefa_entidades_clsdetalleentrega_clsdetalleentrega", "target": "int", "relation": "references", "confidence": "EXTRACTED", "source_file": "SIGEFA.Entidades/clsDetalleEntrega.cs", "source_location": "L11", "weight": 1.0, "context": "field"}, {"source": "sigefa_entidades_clsdetalleentrega_clsdetalleentrega", "target": "int", "relation": "references", "confidence": "EXTRACTED", "source_file": "SIGEFA.Entidades/clsDetalleEntrega.cs", "source_location": "L13", "weight": 1.0, "context": "field"}, {"source": "sigefa_entidades_clsdetalleentrega_clsdetalleentrega", "target": "int", "relation": "references", "confidence": "EXTRACTED", "source_file": "SIGEFA.Entidades/clsDetalleEntrega.cs", "source_location": "L15", "weight": 1.0, "context": "field"}, {"source": "sigefa_entidades_clsdetalleentrega_clsdetalleentrega", "target": "double", "relation": "references", "confidence": "EXTRACTED", "source_file": "SIGEFA.Entidades/clsDetalleEntrega.cs", "source_location": "L17", "weight": 1.0, "context": "field"}, {"source": "sigefa_entidades_clsdetalleentrega_clsdetalleentrega", "target": "string", "relation": "references", "confidence": "EXTRACTED", "source_file": "SIGEFA.Entidades/clsDetalleEntrega.cs", "source_location": "L19", "weight": 1.0, "context": "field"}, {"source": "sigefa_entidades_clsdetalleentrega_clsdetalleentrega", "target": "string", "relation": "references", "confidence": "EXTRACTED", "source_file": "SIGEFA.Entidades/clsDetalleEntrega.cs", "source_location": "L21", "weight": 1.0, "context": "field"}, {"source": "sigefa_entidades_clsdetalleentrega_clsdetalleentrega", "target": "string", "relation": "references", "confidence": "EXTRACTED", "source_file": "SIGEFA.Entidades/clsDetalleEntrega.cs", "source_location": "L23", "weight": 1.0, "context": "field"}], "raw_calls": []}