{"nodes": [{"id": "c_users_qemu_documents_sigefa_legacy_sigefa_interfaces_icotizacion_cs", "label": "ICotizacion.cs", "file_type": "code", "source_file": "SIGEFA.Interfaces/ICotizacion.cs", "source_location": "L1"}, {"id": "sigefa_interfaces_icotizacion_icotizacion", "label": "ICotizacion", "file_type": "code", "source_file": "SIGEFA.Interfaces/ICotizacion.cs", "source_location": "L7"}, {"id": "sigefa_interfaces_icotizacion_icotizacion_insert", "label": ".insert()", "file_type": "code", "source_file": "SIGEFA.Interfaces/ICotizacion.cs", "source_location": "L9"}, {"id": "clscotizacion", "label": "clsCotizacion", "file_type": "code", "source_file": "SIGEFA.Interfaces/ICotizacion.cs", "source_location": "L9"}, {"id": "sigefa_interfaces_icotizacion_icotizacion_update", "label": ".update()", "file_type": "code", "source_file": "SIGEFA.Interfaces/ICotizacion.cs", "source_location": "L11"}, {"id": "sigefa_interfaces_icotizacion_icotizacion_updateaprobado", "label": ".updateAprobado()", "file_type": "code", "source_file": "SIGEFA.Interfaces/ICotizacion.cs", "source_location": "L13"}, {"id": "sigefa_interfaces_icotizacion_icotizacion_duplicarcotizacion", "label": ".DuplicarCotizacion()", "file_type": "code", "source_file": "SIGEFA.Interfaces/ICotizacion.cs", "source_location": "L15"}, {"id": "sigefa_interfaces_icotizacion_icotizacion_validardescuento", "label": ".ValidarDescuento()", "file_type": "code", "source_file": "SIGEFA.Interfaces/ICotizacion.cs", "source_location": "L17"}, {"id": "sigefa_interfaces_icotizacion_icotizacion_delete", "label": ".delete()", "file_type": "code", "source_file": "SIGEFA.Interfaces/ICotizacion.cs", "source_location": "L19"}, {"id": "sigefa_interfaces_icotizacion_icotizacion_insertdetalle", "label": ".insertdetalle()", "file_type": "code", "source_file": "SIGEFA.Interfaces/ICotizacion.cs", "source_location": "L21"}, {"id": "clsdetallecotizacion", "label": "clsDetalleCotizacion", "file_type": "code", "source_file": "SIGEFA.Interfaces/ICotizacion.cs", "source_location": "L21"}, {"id": "sigefa_interfaces_icotizacion_icotizacion_updatedetalle", "label": ".updatedetalle()", "file_type": "code", "source_file": "SIGEFA.Interfaces/ICotizacion.cs", "source_location": "L23"}, {"id": "sigefa_interfaces_icotizacion_icotizacion_deletedetalle", "label": ".deletedetalle()", "file_type": "code", "source_file": "SIGEFA.Interfaces/ICotizacion.cs", "source_location": "L25"}, {"id": "sigefa_interfaces_icotizacion_icotizacion_cargacotizacion", "label": ".CargaCotizacion()", "file_type": "code", "source_file": "SIGEFA.Interfaces/ICotizacion.cs", "source_location": "L27"}, {"id": "sigefa_interfaces_icotizacion_icotizacion_buscacotizacion", "label": ".BuscaCotizacion()", "file_type": "code", "source_file": "SIGEFA.Interfaces/ICotizacion.cs", "source_location": "L29"}, {"id": "sigefa_interfaces_icotizacion_icotizacion_cargadetallecotizacion", "label": ".CargaDetalleCotizacion()", "file_type": "code", "source_file": "SIGEFA.Interfaces/ICotizacion.cs", "source_location": "L31"}, {"id": "sigefa_interfaces_icotizacion_icotizacion_cargadetalle", "label": ".CargaDetalle()", "file_type": "code", "source_file": "SIGEFA.Interfaces/ICotizacion.cs", "source_location": "L33"}, {"id": "datatable", "label": "DataTable", "file_type": "code", "source_file": "SIGEFA.Interfaces/ICotizacion.cs", "source_location": "L33"}, {"id": "sigefa_interfaces_icotizacion_icotizacion_cargadatosrecalcular", "label": ".CargaDatosRecalcular()", "file_type": "code", "source_file": "SIGEFA.Interfaces/ICotizacion.cs", "source_location": "L35"}, {"id": "sigefa_interfaces_icotizacion_icotizacion_cargadetalleventa", "label": ".CargaDetalleVenta()", "file_type": "code", "source_file": "SIGEFA.Interfaces/ICotizacion.cs", "source_location": "L37"}, {"id": "sigefa_interfaces_icotizacion_icotizacion_listacotizaciones", "label": ".ListaCotizaciones()", "file_type": "code", "source_file": "SIGEFA.Interfaces/ICotizacion.cs", "source_location": "L39"}, {"id": "sigefa_interfaces_icotizacion_icotizacion_listacotizacionesxvigente", "label": ".ListaCotizacionesxVigente()", "file_type": "code", "source_file": "SIGEFA.Interfaces/ICotizacion.cs", "source_location": "L41"}, {"id": "datetime", "label": "DateTime", "file_type": "code", "source_file": "SIGEFA.Interfaces/ICotizacion.cs", "source_location": "L41"}, {"id": "sigefa_interfaces_icotizacion_icotizacion_cotizacionesvencidas", "label": ".CotizacionesVencidas()", "file_type": "code", "source_file": "SIGEFA.Interfaces/ICotizacion.cs", "source_location": "L43"}], "edges": [{"source": "c_users_qemu_documents_sigefa_legacy_sigefa_interfaces_icotizacion_cs", "target": "system", "relation": "imports", "context": "import", "confidence": "EXTRACTED", "source_file": "SIGEFA.Interfaces/ICotizacion.cs", "source_location": "L1", "weight": 1.0}, {"source": "c_users_qemu_documents_sigefa_legacy_sigefa_interfaces_icotizacion_cs", "target": "data", "relation": "imports", "context": "import", "confidence": "EXTRACTED", "source_file": "SIGEFA.Interfaces/ICotizacion.cs", "source_location": "L2", "weight": 1.0}, {"source": "c_users_qemu_documents_sigefa_legacy_sigefa_interfaces_icotizacion_cs", "target": "entidades", "relation": "imports", "context": "import", "confidence": "EXTRACTED", "source_file": "SIGEFA.Interfaces/ICotizacion.cs", "source_location": "L3", "weight": 1.0}, {"source": "c_users_qemu_documents_sigefa_legacy_sigefa_interfaces_icotizacion_cs", "target": "sigefa_interfaces_icotizacion_icotizacion", "relation": "contains", "confidence": "EXTRACTED", "source_file": "SIGEFA.Interfaces/ICotizacion.cs", "source_location": "L7", "weight": 1.0}, {"source": "sigefa_interfaces_icotizacion_icotizacion", "target": "sigefa_interfaces_icotizacion_icotizacion_insert", "relation": "method", "confidence": "EXTRACTED", "source_file": "SIGEFA.Interfaces/ICotizacion.cs", "source_location": "L9", "weight": 1.0}, {"source": "sigefa_interfaces_icotizacion_icotizacion_insert", "target": "clscotizacion", "relation": "references", "confidence": "EXTRACTED", "source_file": "SIGEFA.Interfaces/ICotizacion.cs", "source_location": "L9", "weight": 1.0, "context": "parameter_type"}, {"source": "sigefa_interfaces_icotizacion_icotizacion", "target": "sigefa_interfaces_icotizacion_icotizacion_update", "relation": "method", "confidence": "EXTRACTED", "source_file": "SIGEFA.Interfaces/ICotizacion.cs", "source_location": "L11", "weight": 1.0}, {"source": "sigefa_interfaces_icotizacion_icotizacion_update", "target": "clscotizacion", "relation": "references", "confidence": "EXTRACTED", "source_file": "SIGEFA.Interfaces/ICotizacion.cs", "source_location": "L11", "weight": 1.0, "context": "parameter_type"}, {"source": "sigefa_interfaces_icotizacion_icotizacion", "target": "sigefa_interfaces_icotizacion_icotizacion_updateaprobado", "relation": "method", "confidence": "EXTRACTED", "source_file": "SIGEFA.Interfaces/ICotizacion.cs", "source_location": "L13", "weight": 1.0}, {"source": "sigefa_interfaces_icotizacion_icotizacion", "target": "sigefa_interfaces_icotizacion_icotizacion_duplicarcotizacion", "relation": "method", "confidence": "EXTRACTED", "source_file": "SIGEFA.Interfaces/ICotizacion.cs", "source_location": "L15", "weight": 1.0}, {"source": "sigefa_interfaces_icotizacion_icotizacion", "target": "sigefa_interfaces_icotizacion_icotizacion_validardescuento", "relation": "method", "confidence": "EXTRACTED", "source_file": "SIGEFA.Interfaces/ICotizacion.cs", "source_location": "L17", "weight": 1.0}, {"source": "sigefa_interfaces_icotizacion_icotizacion", "target": "sigefa_interfaces_icotizacion_icotizacion_delete", "relation": "method", "confidence": "EXTRACTED", "source_file": "SIGEFA.Interfaces/ICotizacion.cs", "source_location": "L19", "weight": 1.0}, {"source": "sigefa_interfaces_icotizacion_icotizacion", "target": "sigefa_interfaces_icotizacion_icotizacion_insertdetalle", "relation": "method", "confidence": "EXTRACTED", "source_file": "SIGEFA.Interfaces/ICotizacion.cs", "source_location": "L21", "weight": 1.0}, {"source": "sigefa_interfaces_icotizacion_icotizacion_insertdetalle", "target": "clsdetallecotizacion", "relation": "references", "confidence": "EXTRACTED", "source_file": "SIGEFA.Interfaces/ICotizacion.cs", "source_location": "L21", "weight": 1.0, "context": "parameter_type"}, {"source": "sigefa_interfaces_icotizacion_icotizacion", "target": "sigefa_interfaces_icotizacion_icotizacion_updatedetalle", "relation": "method", "confidence": "EXTRACTED", "source_file": "SIGEFA.Interfaces/ICotizacion.cs", "source_location": "L23", "weight": 1.0}, {"source": "sigefa_interfaces_icotizacion_icotizacion_updatedetalle", "target": "clsdetallecotizacion", "relation": "references", "confidence": "EXTRACTED", "source_file": "SIGEFA.Interfaces/ICotizacion.cs", "source_location": "L23", "weight": 1.0, "context": "parameter_type"}, {"source": "sigefa_interfaces_icotizacion_icotizacion", "target": "sigefa_interfaces_icotizacion_icotizacion_deletedetalle", "relation": "method", "confidence": "EXTRACTED", "source_file": "SIGEFA.Interfaces/ICotizacion.cs", "source_location": "L25", "weight": 1.0}, {"source": "sigefa_interfaces_icotizacion_icotizacion", "target": "sigefa_interfaces_icotizacion_icotizacion_cargacotizacion", "relation": "method", "confidence": "EXTRACTED", "source_file": "SIGEFA.Interfaces/ICotizacion.cs", "source_location": "L27", "weight": 1.0}, {"source": "sigefa_interfaces_icotizacion_icotizacion_cargacotizacion", "target": "clscotizacion", "relation": "references", "confidence": "EXTRACTED", "source_file": "SIGEFA.Interfaces/ICotizacion.cs", "source_location": "L27", "weight": 1.0, "context": "return_type"}, {"source": "sigefa_interfaces_icotizacion_icotizacion", "target": "sigefa_interfaces_icotizacion_icotizacion_buscacotizacion", "relation": "method", "confidence": "EXTRACTED", "source_file": "SIGEFA.Interfaces/ICotizacion.cs", "source_location": "L29", "weight": 1.0}, {"source": "sigefa_interfaces_icotizacion_icotizacion_buscacotizacion", "target": "clscotizacion", "relation": "references", "confidence": "EXTRACTED", "source_file": "SIGEFA.Interfaces/ICotizacion.cs", "source_location": "L29", "weight": 1.0, "context": "return_type"}, {"source": "sigefa_interfaces_icotizacion_icotizacion", "target": "sigefa_interfaces_icotizacion_icotizacion_cargadetallecotizacion", "relation": "method", "confidence": "EXTRACTED", "source_file": "SIGEFA.Interfaces/ICotizacion.cs", "source_location": "L31", "weight": 1.0}, {"source": "sigefa_interfaces_icotizacion_icotizacion_cargadetallecotizacion", "target": "clsdetallecotizacion", "relation": "references", "confidence": "EXTRACTED", "source_file": "SIGEFA.Interfaces/ICotizacion.cs", "source_location": "L31", "weight": 1.0, "context": "return_type"}, {"source": "sigefa_interfaces_icotizacion_icotizacion", "target": "sigefa_interfaces_icotizacion_icotizacion_cargadetalle", "relation": "method", "confidence": "EXTRACTED", "source_file": "SIGEFA.Interfaces/ICotizacion.cs", "source_location": "L33", "weight": 1.0}, {"source": "sigefa_interfaces_icotizacion_icotizacion_cargadetalle", "target": "datatable", "relation": "references", "confidence": "EXTRACTED", "source_file": "SIGEFA.Interfaces/ICotizacion.cs", "source_location": "L33", "weight": 1.0, "context": "return_type"}, {"source": "sigefa_interfaces_icotizacion_icotizacion", "target": "sigefa_interfaces_icotizacion_icotizacion_cargadatosrecalcular", "relation": "method", "confidence": "EXTRACTED", "source_file": "SIGEFA.Interfaces/ICotizacion.cs", "source_location": "L35", "weight": 1.0}, {"source": "sigefa_interfaces_icotizacion_icotizacion_cargadatosrecalcular", "target": "datatable", "relation": "references", "confidence": "EXTRACTED", "source_file": "SIGEFA.Interfaces/ICotizacion.cs", "source_location": "L35", "weight": 1.0, "context": "return_type"}, {"source": "sigefa_interfaces_icotizacion_icotizacion", "target": "sigefa_interfaces_icotizacion_icotizacion_cargadetalleventa", "relation": "method", "confidence": "EXTRACTED", "source_file": "SIGEFA.Interfaces/ICotizacion.cs", "source_location": "L37", "weight": 1.0}, {"source": "sigefa_interfaces_icotizacion_icotizacion_cargadetalleventa", "target": "datatable", "relation": "references", "confidence": "EXTRACTED", "source_file": "SIGEFA.Interfaces/ICotizacion.cs", "source_location": "L37", "weight": 1.0, "context": "return_type"}, {"source": "sigefa_interfaces_icotizacion_icotizacion", "target": "sigefa_interfaces_icotizacion_icotizacion_listacotizaciones", "relation": "method", "confidence": "EXTRACTED", "source_file": "SIGEFA.Interfaces/ICotizacion.cs", "source_location": "L39", "weight": 1.0}, {"source": "sigefa_interfaces_icotizacion_icotizacion_listacotizaciones", "target": "datatable", "relation": "references", "confidence": "EXTRACTED", "source_file": "SIGEFA.Interfaces/ICotizacion.cs", "source_location": "L39", "weight": 1.0, "context": "return_type"}, {"source": "sigefa_interfaces_icotizacion_icotizacion", "target": "sigefa_interfaces_icotizacion_icotizacion_listacotizacionesxvigente", "relation": "method", "confidence": "EXTRACTED", "source_file": "SIGEFA.Interfaces/ICotizacion.cs", "source_location": "L41", "weight": 1.0}, {"source": "sigefa_interfaces_icotizacion_icotizacion_listacotizacionesxvigente", "target": "datetime", "relation": "references", "confidence": "EXTRACTED", "source_file": "SIGEFA.Interfaces/ICotizacion.cs", "source_location": "L41", "weight": 1.0, "context": "parameter_type"}, {"source": "sigefa_interfaces_icotizacion_icotizacion_listacotizacionesxvigente", "target": "datetime", "relation": "references", "confidence": "EXTRACTED", "source_file": "SIGEFA.Interfaces/ICotizacion.cs", "source_location": "L41", "weight": 1.0, "context": "parameter_type"}, {"source": "sigefa_interfaces_icotizacion_icotizacion_listacotizacionesxvigente", "target": "datatable", "relation": "references", "confidence": "EXTRACTED", "source_file": "SIGEFA.Interfaces/ICotizacion.cs", "source_location": "L41", "weight": 1.0, "context": "return_type"}, {"source": "sigefa_interfaces_icotizacion_icotizacion", "target": "sigefa_interfaces_icotizacion_icotizacion_cotizacionesvencidas", "relation": "method", "confidence": "EXTRACTED", "source_file": "SIGEFA.Interfaces/ICotizacion.cs", "source_location": "L43", "weight": 1.0}], "raw_calls": []}